vinylnet/__init__.py
vinylnet/core.py
vinylnet-1.2.0.dist-info/licenses/LICENSE
vinylnet-1.2.0.dist-info/METADATA
vinylnet-1.2.0.dist-info/WHEEL
vinylnet-1.2.0.dist-info/top_level.txt
vinylnet-1.2.0.dist-info/RECORD
