Metadata-Version: 2.4
Name: vinylnet
Version: 1.2.0
Summary: Librería para convertir audio en representaciones visuales espirales (Spiral Coordinate Mapping) para IA y Alta Fidelidad.
Author-email: Emiliano Cuellar <emiliano446152@gmail.com>
License: MIT
Keywords: audio,visualization,ai,machine learning,spectrogram,signal processing
Classifier: Development Status :: 3 - Alpha
Classifier: Intended Audience :: Developers
Classifier: Intended Audience :: Science/Research
Classifier: Topic :: Multimedia :: Sound/Audio :: Analysis
Classifier: Topic :: Scientific/Engineering :: Artificial Intelligence
Classifier: License :: OSI Approved :: MIT License
Classifier: Programming Language :: Python :: 3
Classifier: Programming Language :: Python :: 3.8
Classifier: Programming Language :: Python :: 3.9
Classifier: Programming Language :: Python :: 3.10
Classifier: Operating System :: OS Independent
Requires-Python: >=3.8
License-File: LICENSE
Requires-Dist: numpy
Requires-Dist: opencv-python
Requires-Dist: librosa
Requires-Dist: soundfile
Dynamic: license-file
